{
  "id": "2631966",
  "name": "blockchain",
  "font_family": "iconfont",
  "css_prefix_text": "icon-",
  "description": "溯源",
  "glyphs": [
    {
      "icon_id": "24385248",
      "name": "packing",
      "font_class": "packing",
      "unicode": "e619",
      "unicode_decimal": 58905
    },
    {
      "icon_id": "24381208",
      "name": "activation",
      "font_class": "activation",
      "unicode": "e61a",
      "unicode_decimal": 58906
    },
    {
      "icon_id": "22580792",
      "name": "add_photo",
      "font_class": "add_photo",
      "unicode": "e618",
      "unicode_decimal": 58904
    },
    {
      "icon_id": "22466464",
      "name": "消息",
      "font_class": "xiaoxi",
      "unicode": "e616",
      "unicode_decimal": 58902
    },
    {
      "icon_id": "22466470",
      "name": "员工管理",
      "font_class": "yuangongguanli",
      "unicode": "e617",
      "unicode_decimal": 58903
    },
    {
      "icon_id": "22456947",
      "name": "briefcase_outlined",
      "font_class": "briefcase_outlined",
      "unicode": "e606",
      "unicode_decimal": 58886
    },
    {
      "icon_id": "22456948",
      "name": "brightness__outlined",
      "font_class": "brightness__outlined",
      "unicode": "e607",
      "unicode_decimal": 58887
    },
    {
      "icon_id": "22456949",
      "name": "canvas_text",
      "font_class": "canvas_text",
      "unicode": "e608",
      "unicode_decimal": 58888
    },
    {
      "icon_id": "22456950",
      "name": "file_add_outlined",
      "font_class": "file_add_outlined",
      "unicode": "e609",
      "unicode_decimal": 58889
    },
    {
      "icon_id": "22456951",
      "name": "flag_outlined",
      "font_class": "flag_outlined",
      "unicode": "e60a",
      "unicode_decimal": 58890
    },
    {
      "icon_id": "22456952",
      "name": "focus",
      "font_class": "focus",
      "unicode": "e60b",
      "unicode_decimal": 58891
    },
    {
      "icon_id": "22456953",
      "name": "qr_code",
      "font_class": "qr_code",
      "unicode": "e60c",
      "unicode_decimal": 58892
    },
    {
      "icon_id": "22456954",
      "name": "notifications_outlined",
      "font_class": "notifications_outlined",
      "unicode": "e60d",
      "unicode_decimal": 58893
    },
    {
      "icon_id": "22456955",
      "name": "inbox",
      "font_class": "inbox",
      "unicode": "e60e",
      "unicode_decimal": 58894
    },
    {
      "icon_id": "22456956",
      "name": "settings_vs_outlined",
      "font_class": "settings_vs_outlined",
      "unicode": "e60f",
      "unicode_decimal": 58895
    },
    {
      "icon_id": "22456957",
      "name": "vertical_align_top",
      "font_class": "vertical_align_top",
      "unicode": "e610",
      "unicode_decimal": 58896
    },
    {
      "icon_id": "22456958",
      "name": "scan",
      "font_class": "scan",
      "unicode": "e611",
      "unicode_decimal": 58897
    },
    {
      "icon_id": "22456959",
      "name": "hourglass_outlined",
      "font_class": "hourglass_outlined",
      "unicode": "e612",
      "unicode_decimal": 58898
    },
    {
      "icon_id": "22456960",
      "name": "spa_outlined",
      "font_class": "spa_outlined",
      "unicode": "e613",
      "unicode_decimal": 58899
    },
    {
      "icon_id": "22456961",
      "name": "sign_out",
      "font_class": "sign_out",
      "unicode": "e614",
      "unicode_decimal": 58900
    },
    {
      "icon_id": "22456962",
      "name": "user_big_outlined",
      "font_class": "user_big_outlined",
      "unicode": "e615",
      "unicode_decimal": 58901
    }
  ]
}
